MANIFEST.in
README.rst
pysitemap.py
setup.py
pysitemap.egg-info/PKG-INFO
pysitemap.egg-info/SOURCES.txt
pysitemap.egg-info/dependency_links.txt
pysitemap.egg-info/top_level.txt