Metadata-Version: 1.0
Name: pysitemap
Version: 0.5
Summary: A Python library for generating sitemap
Home-page: https://github.com/vitalvas/pysitemap
Author: VitalVas
Author-email: UNKNOWN
License: BSD
Keywords: sitemap xml
Platform: any
Classifier: Development Status :: 4 - Beta
Classifier: Intended Audience :: Developers
Classifier: Operating System :: OS Independent
Classifier: License :: OSI Approved :: BSD License
Classifier: Programming Language :: Python
Classifier: Topic :: Software Development
Classifier: Programming Language :: Python :: 2.6
Classifier: Programming Language :: Python :: 2.7
